{
    "results_found": 4568,
    "results_start": 0,
    "results_shown": 20,
    "restaurants": [
      {
        "restaurant": {
          "R": {
            "res_id": 18387851
          },
          "apikey": "1b4ca21099641932b900452285be769e",
          "id": "18387851",
          "name": "One Eighty Coffee",
          "url": "https://www.zomato.com/bandung/one-eighty-coffee-dago?utm_source=api_basic_user&utm_medium=api&utm_campaign=v2.1",
          "location": {
            "address": "Jl. Ganeca No. 3, Dago, Bandung",
            "locality": "Dago",
            "city": "Bandung",
            "city_id": 11052,
            "latitude": "-6.8938320000",
            "longitude": "107.6123020000",
            "zipcode": "",
            "country_id": 94,
            "locality_verbose": "Dago, Bandung"
          },
          "switch_to_order_menu": 0,
          "cuisines": "Cafe, Desserts, Coffee, Tea",
          "average_cost_for_two": 150000,
          "price_range": 3,
          "currency": "IDR",
          "offers": [],
          "opentable_support": 0,
          "is_zomato_book_res": 0,
          "mezzo_provider": "OTHER",
          "is_book_form_web_view": 0,
          "book_form_web_view_url": "",
          "book_again_url": "",
          "thumb": "https://b.zmtcdn.com/data/res_imagery/18387851_RESTAURANT_956761a6f47856c16a0fbc4593ad73aa.jpg?fit=around%7C200%3A200&crop=200%3A200%3B%2A%2C%2A",
          "user_rating": {
            "aggregate_rating": "4.6",
            "rating_text": "Excellent",
            "rating_color": "3F7E00",
            "votes": "696"
          },
          "photos_url": "https://www.zomato.com/bandung/one-eighty-coffee-dago/photos?utm_source=api_basic_user&utm_medium=api&utm_campaign=v2.1#tabtop",
          "menu_url": "https://www.zomato.com/bandung/one-eighty-coffee-dago/menu?utm_source=api_basic_user&utm_medium=api&utm_campaign=v2.1&openSwipeBox=menu&showMinimal=1#tabtop",
          "featured_image": "https://b.zmtcdn.com/data/res_imagery/18387851_RESTAURANT_956761a6f47856c16a0fbc4593ad73aa.jpg",
          "has_online_delivery": 0,
          "is_delivering_now": 0,
          "include_bogo_offers": true,
          "deeplink": "zomato://restaurant/18387851",
          "is_table_reservation_supported": 0,
          "has_table_booking": 0,
          "events_url": "https://www.zomato.com/bandung/one-eighty-coffee-dago/events#tabtop?utm_source=api_basic_user&utm_medium=api&utm_campaign=v2.1",
          "establishment_types": []
        }
      },
      {
        "restaurant": {
          "R": {
            "res_id": 18619623
          },
          "apikey": "1b4ca21099641932b900452285be769e",
          "id": "18619623",
          "name": "Gyu-Kaku Japanese BBQ",
          "url": "https://www.zomato.com/bandung/gyu-kaku-japanese-bbq-bandung-wetan?utm_source=api_basic_user&utm_medium=api&utm_campaign=v2.1",
          "location": {
            "address": "Jl. Pangeran Kornel No. 7, Bandung Wetan, Bandung",
            "locality": "Bandung Wetan",
            "city": "Bandung",
            "city_id": 11052,
            "latitude": "-6.8993770000",
            "longitude": "107.6134490000",
            "zipcode": "",
            "country_id": 94,
            "locality_verbose": "Bandung Wetan, Bandung"
          },
          "switch_to_order_menu": 0,
          "cuisines": "Japanese",
          "average_cost_for_two": 300000,
          "price_range": 3,
          "currency": "IDR",
          "offers": [],
          "opentable_support": 0,
          "is_zomato_book_res": 0,
          "mezzo_provider": "OTHER",
          "is_book_form_web_view": 0,
          "book_form_web_view_url": "",
          "book_again_url": "",
          "thumb": "https://b.zmtcdn.com/data/res_imagery/18619623_RESTAURANT_c0058306ab411f43a41ef3bfe5979b84.jpg?fit=around%7C200%3A200&crop=200%3A200%3B%2A%2C%2A",
          "user_rating": {
            "aggregate_rating": "4.9",
            "rating_text": "Excellent",
            "rating_color": "3F7E00",
            "votes": "1427"
          },
          "photos_url": "https://www.zomato.com/bandung/gyu-kaku-japanese-bbq-bandung-wetan/photos?utm_source=api_basic_user&utm_medium=api&utm_campaign=v2.1#tabtop",
          "menu_url": "https://www.zomato.com/bandung/gyu-kaku-japanese-bbq-bandung-wetan/menu?utm_source=api_basic_user&utm_medium=api&utm_campaign=v2.1&openSwipeBox=menu&showMinimal=1#tabtop",
          "featured_image": "https://b.zmtcdn.com/data/res_imagery/18619623_RESTAURANT_c0058306ab411f43a41ef3bfe5979b84.jpg",
          "has_online_delivery": 0,
          "is_delivering_now": 0,
          "include_bogo_offers": true,
          "deeplink": "zomato://restaurant/18619623",
          "is_table_reservation_supported": 0,
          "has_table_booking": 0,
          "events_url": "https://www.zomato.com/bandung/gyu-kaku-japanese-bbq-bandung-wetan/events#tabtop?utm_source=api_basic_user&utm_medium=api&utm_campaign=v2.1",
          "establishment_types": []
        }
      },
      {
        "restaurant": {
          "R": {
            "res_id": 18405613
          },
          "apikey": "1b4ca21099641932b900452285be769e",
          "id": "18405613",
          "name": "Se'i Sapi Lamalera",
          "url": "https://www.zomato.com/bandung/sei-sapi-lamalera-dago?utm_source=api_basic_user&utm_medium=api&utm_campaign=v2.1",
          "location": {
            "address": "Jl. Bagus Rangin No. 24A, Dago, Bandung",
            "locality": "Dago",
            "city": "Bandung",
            "city_id": 11052,
            "latitude": "-6.8981550000",
            "longitude": "107.6173030000",
            "zipcode": "",
            "country_id": 94,
            "locality_verbose": "Dago, Bandung"
          },
          "switch_to_order_menu": 0,
          "cuisines": "Indonesian",
          "average_cost_for_two": 150000,
          "price_range": 3,
          "currency": "IDR",
          "offers": [],
          "opentable_support": 0,
          "is_zomato_book_res": 0,
          "mezzo_provider": "OTHER",
          "is_book_form_web_view": 0,
          "book_form_web_view_url": "",
          "book_again_url": "",
          "thumb": "https://b.zmtcdn.com/data/res_imagery/18405613_RESTAURANT_abdc6b266340941111abdb4a754f252a.jpg?fit=around%7C200%3A200&crop=200%3A200%3B%2A%2C%2A",
          "user_rating": {
            "aggregate_rating": "4.8",
            "rating_text": "Excellent",
            "rating_color": "3F7E00",
            "votes": "517"
          },
          "photos_url": "https://www.zomato.com/bandung/sei-sapi-lamalera-dago/photos?utm_source=api_basic_user&utm_medium=api&utm_campaign=v2.1#tabtop",
          "menu_url": "https://www.zomato.com/bandung/sei-sapi-lamalera-dago/menu?utm_source=api_basic_user&utm_medium=api&utm_campaign=v2.1&openSwipeBox=menu&showMinimal=1#tabtop",
          "featured_image": "https://b.zmtcdn.com/data/res_imagery/18405613_RESTAURANT_abdc6b266340941111abdb4a754f252a.jpg",
          "has_online_delivery": 0,
          "is_delivering_now": 0,
          "include_bogo_offers": true,
          "deeplink": "zomato://restaurant/18405613",
          "is_table_reservation_supported": 0,
          "has_table_booking": 0,
          "events_url": "https://www.zomato.com/bandung/sei-sapi-lamalera-dago/events#tabtop?utm_source=api_basic_user&utm_medium=api&utm_campaign=v2.1",
          "establishment_types": []
        }
      },
      {
        "restaurant": {
          "R": {
            "res_id": 18403125
          },
          "apikey": "1b4ca21099641932b900452285be769e",
          "id": "18403125",
          "name": "Gormeteria",
          "url": "https://www.zomato.com/bandung/gormeteria-pasirkaliki?utm_source=api_basic_user&utm_medium=api&utm_campaign=v2.1",
          "location": {
            "address": "Jl. Pasirkaliki No. 176, Pasirkaliki, Bandung",
            "locality": "Pasirkaliki",
            "city": "Bandung",
            "city_id": 11052,
            "latitude": "-6.9015680000",
            "longitude": "107.5976120000",
            "zipcode": "",
            "country_id": 94,
            "locality_verbose": "Pasirkaliki, Bandung"
          },
          "switch_to_order_menu": 0,
          "cuisines": "Western, Asian",
          "average_cost_for_two": 180000,
          "price_range": 3,
          "currency": "IDR",
          "offers": [],
          "opentable_support": 0,
          "is_zomato_book_res": 0,
          "mezzo_provider": "OTHER",
          "is_book_form_web_view": 0,
          "book_form_web_view_url": "",
          "book_again_url": "",
          "thumb": "https://b.zmtcdn.com/data/res_imagery/18403125_RESTAURANT_369bc89aa74f97e870235074c3a23d6c.jpg?fit=around%7C200%3A200&crop=200%3A200%3B%2A%2C%2A",
          "user_rating": {
            "aggregate_rating": "4.7",
            "rating_text": "Excellent",
            "rating_color": "3F7E00",
            "votes": "529"
          },
          "photos_url": "https://www.zomato.com/bandung/gormeteria-pasirkaliki/photos?utm_source=api_basic_user&utm_medium=api&utm_campaign=v2.1#tabtop",
          "menu_url": "https://www.zomato.com/bandung/gormeteria-pasirkaliki/menu?utm_source=api_basic_user&utm_medium=api&utm_campaign=v2.1&openSwipeBox=menu&showMinimal=1#tabtop",
          "featured_image": "https://b.zmtcdn.com/data/res_imagery/18403125_RESTAURANT_369bc89aa74f97e870235074c3a23d6c.jpg",
          "has_online_delivery": 0,
          "is_delivering_now": 0,
          "include_bogo_offers": true,
          "deeplink": "zomato://restaurant/18403125",
          "is_table_reservation_supported": 0,
          "has_table_booking": 0,
          "events_url": "https://www.zomato.com/bandung/gormeteria-pasirkaliki/events#tabtop?utm_source=api_basic_user&utm_medium=api&utm_campaign=v2.1",
          "establishment_types": []
        }
      },
      {
        "restaurant": {
          "R": {
            "res_id": 18400534
          },
          "apikey": "1b4ca21099641932b900452285be769e",
          "id": "18400534",
          "name": "Glosis",
          "url": "https://www.zomato.com/bandung/glosis-riau?utm_source=api_basic_user&utm_medium=api&utm_campaign=v2.1",
          "location": {
            "address": "Jl. Citarum, No. 12, Riau, Bandung",
            "locality": "Riau",
            "city": "Bandung",
            "city_id": 11052,
            "latitude": "-6.9048976307",
            "longitude": "107.6227485761",
            "zipcode": "",
            "country_id": 94,
            "locality_verbose": "Riau, Bandung"
          },
          "switch_to_order_menu": 0,
          "cuisines": "Western, European, Asian",
          "average_cost_for_two": 150000,
          "price_range": 3,
          "currency": "IDR",
          "offers": [],
          "opentable_support": 0,
          "is_zomato_book_res": 0,
          "mezzo_provider": "OTHER",
          "is_book_form_web_view": 0,
          "book_form_web_view_url": "",
          "book_again_url": "",
          "thumb": "https://b.zmtcdn.com/data/reviews_photos/efa/5ef1869d30c3df3165135d88019fcefa_1528081443.jpg?fit=around%7C200%3A200&crop=200%3A200%3B%2A%2C%2A",
          "user_rating": {
            "aggregate_rating": "4.6",
            "rating_text": "Excellent",
            "rating_color": "3F7E00",
            "votes": "264"
          },
          "photos_url": "https://www.zomato.com/bandung/glosis-riau/photos?utm_source=api_basic_user&utm_medium=api&utm_campaign=v2.1#tabtop",
          "menu_url": "https://www.zomato.com/bandung/glosis-riau/menu?utm_source=api_basic_user&utm_medium=api&utm_campaign=v2.1&openSwipeBox=menu&showMinimal=1#tabtop",
          "featured_image": "https://b.zmtcdn.com/data/reviews_photos/efa/5ef1869d30c3df3165135d88019fcefa_1528081443.jpg",
          "has_online_delivery": 0,
          "is_delivering_now": 0,
          "include_bogo_offers": true,
          "deeplink": "zomato://restaurant/18400534",
          "is_table_reservation_supported": 0,
          "has_table_booking": 0,
          "events_url": "https://www.zomato.com/bandung/glosis-riau/events#tabtop?utm_source=api_basic_user&utm_medium=api&utm_campaign=v2.1",
          "establishment_types": []
        }
      },
      {
        "restaurant": {
          "R": {
            "res_id": 18575667
          },
          "apikey": "1b4ca21099641932b900452285be769e",
          "id": "18575667",
          "name": "Sate Taichan Goreng",
          "url": "https://www.zomato.com/bandung/sate-taichan-goreng-sumurbandung?utm_source=api_basic_user&utm_medium=api&utm_campaign=v2.1",
          "location": {
            "address": "Jl. Banda No. 10, Sumurbandung, Bandung",
            "locality": "Sumurbandung",
            "city": "Bandung",
            "city_id": 11052,
            "latitude": "-6.910927",
            "longitude": "107.6176200000",
            "zipcode": "",
            "country_id": 94,
            "locality_verbose": "Sumurbandung, Bandung"
          },
          "switch_to_order_menu": 0,
          "cuisines": "Satay",
          "average_cost_for_two": 60000,
          "price_range": 1,
          "currency": "IDR",
          "offers": [],
          "opentable_support": 0,
          "is_zomato_book_res": 0,
          "mezzo_provider": "OTHER",
          "is_book_form_web_view": 0,
          "book_form_web_view_url": "",
          "book_again_url": "",
          "thumb": "https://b.zmtcdn.com/data/res_imagery/18575667_RESTAURANT_01bba1c964ac58a7f453a009419c0c6a.jpg?fit=around%7C200%3A200&crop=200%3A200%3B%2A%2C%2A",
          "user_rating": {
            "aggregate_rating": "4.7",
            "rating_text": "Excellent",
            "rating_color": "3F7E00",
            "votes": "831"
          },
          "photos_url": "https://www.zomato.com/bandung/sate-taichan-goreng-sumurbandung/photos?utm_source=api_basic_user&utm_medium=api&utm_campaign=v2.1#tabtop",
          "menu_url": "https://www.zomato.com/bandung/sate-taichan-goreng-sumurbandung/menu?utm_source=api_basic_user&utm_medium=api&utm_campaign=v2.1&openSwipeBox=menu&showMinimal=1#tabtop",
          "featured_image": "https://b.zmtcdn.com/data/res_imagery/18575667_RESTAURANT_01bba1c964ac58a7f453a009419c0c6a.jpg",
          "has_online_delivery": 0,
          "is_delivering_now": 0,
          "include_bogo_offers": true,
          "deeplink": "zomato://restaurant/18575667",
          "is_table_reservation_supported": 0,
          "has_table_booking": 0,
          "events_url": "https://www.zomato.com/bandung/sate-taichan-goreng-sumurbandung/events#tabtop?utm_source=api_basic_user&utm_medium=api&utm_campaign=v2.1",
          "establishment_types": []
        }
      },
      {
        "restaurant": {
          "R": {
            "res_id": 18404865
          },
          "apikey": "1b4ca21099641932b900452285be769e",
          "id": "18404865",
          "name": "Sejiwa Coffee",
          "url": "https://www.zomato.com/bandung/sejiwa-coffee-riau?utm_source=api_basic_user&utm_medium=api&utm_campaign=v2.1",
          "location": {
            "address": "Jl. Progo No.15, Riau, Bandung",
            "locality": "Riau",
            "city": "Bandung",
            "city_id": 11052,
            "latitude": "-6.9043030000",
            "longitude": "107.6185410000",
            "zipcode": "",
            "country_id": 94,
            "locality_verbose": "Riau, Bandung"
          },
          "switch_to_order_menu": 0,
          "cuisines": "Cafe, Desserts, Coffee",
          "average_cost_for_two": 100000,
          "price_range": 2,
          "currency": "IDR",
          "offers": [],
          "opentable_support": 0,
          "is_zomato_book_res": 0,
          "mezzo_provider": "OTHER",
          "is_book_form_web_view": 0,
          "book_form_web_view_url": "",
          "book_again_url": "",
          "thumb": "https://b.zmtcdn.com/data/res_imagery/18404865_RESTAURANT_4fea1a2440432bff040dfba804691b2b.jpg?fit=around%7C200%3A200&crop=200%3A200%3B%2A%2C%2A",
          "user_rating": {
            "aggregate_rating": "4.3",
            "rating_text": "Sangat Baik",
            "rating_color": "5BA829",
            "votes": "483"
          },
          "photos_url": "https://www.zomato.com/bandung/sejiwa-coffee-riau/photos?utm_source=api_basic_user&utm_medium=api&utm_campaign=v2.1#tabtop",
          "menu_url": "https://www.zomato.com/bandung/sejiwa-coffee-riau/menu?utm_source=api_basic_user&utm_medium=api&utm_campaign=v2.1&openSwipeBox=menu&showMinimal=1#tabtop",
          "featured_image": "https://b.zmtcdn.com/data/res_imagery/18404865_RESTAURANT_4fea1a2440432bff040dfba804691b2b.jpg",
          "has_online_delivery": 0,
          "is_delivering_now": 0,
          "include_bogo_offers": true,
          "deeplink": "zomato://restaurant/18404865",
          "is_table_reservation_supported": 0,
          "has_table_booking": 0,
          "events_url": "https://www.zomato.com/bandung/sejiwa-coffee-riau/events#tabtop?utm_source=api_basic_user&utm_medium=api&utm_campaign=v2.1",
          "establishment_types": []
        }
      },
      {
        "restaurant": {
          "R": {
            "res_id": 18387855
          },
          "apikey": "1b4ca21099641932b900452285be769e",
          "id": "18387855",
          "name": "Miss Bee Providore",
          "url": "https://www.zomato.com/bandung/miss-bee-providore-ciumbuleuit?utm_source=api_basic_user&utm_medium=api&utm_campaign=v2.1",
          "location": {
            "address": "Jl. Rancabentang No. 11A, Ciumbuleuit, Bandung",
            "locality": "Ciumbuleuit",
            "city": "Bandung",
            "city_id": 11052,
            "latitude": "-6.8683855245",
            "longitude": "107.6093053445",
            "zipcode": "",
            "country_id": 94,
            "locality_verbose": "Ciumbuleuit, Bandung"
          },
          "switch_to_order_menu": 0,
          "cuisines": "European, Asian",
          "average_cost_for_two": 150000,
          "price_range": 3,
          "currency": "IDR",
          "offers": [],
          "opentable_support": 0,
          "is_zomato_book_res": 0,
          "mezzo_provider": "OTHER",
          "is_book_form_web_view": 0,
          "book_form_web_view_url": "",
          "book_again_url": "",
          "thumb": "https://b.zmtcdn.com/data/res_imagery/18387855_RESTAURANT_ea1271500064ae39c600dcf6b8f3100b.jpg?fit=around%7C200%3A200&crop=200%3A200%3B%2A%2C%2A",
          "user_rating": {
            "aggregate_rating": "4.6",
            "rating_text": "Excellent",
            "rating_color": "3F7E00",
            "votes": "426"
          },
          "photos_url": "https://www.zomato.com/bandung/miss-bee-providore-ciumbuleuit/photos?utm_source=api_basic_user&utm_medium=api&utm_campaign=v2.1#tabtop",
          "menu_url": "https://www.zomato.com/bandung/miss-bee-providore-ciumbuleuit/menu?utm_source=api_basic_user&utm_medium=api&utm_campaign=v2.1&openSwipeBox=menu&showMinimal=1#tabtop",
          "featured_image": "https://b.zmtcdn.com/data/res_imagery/18387855_RESTAURANT_ea1271500064ae39c600dcf6b8f3100b.jpg",
          "has_online_delivery": 0,
          "is_delivering_now": 0,
          "include_bogo_offers": true,
          "deeplink": "zomato://restaurant/18387855",
          "is_table_reservation_supported": 0,
          "has_table_booking": 0,
          "events_url": "https://www.zomato.com/bandung/miss-bee-providore-ciumbuleuit/events#tabtop?utm_source=api_basic_user&utm_medium=api&utm_campaign=v2.1",
          "establishment_types": []
        }
      },
      {
        "restaurant": {
          "R": {
            "res_id": 18764005
          },
          "apikey": "1b4ca21099641932b900452285be769e",
          "id": "18764005",
          "name": "Sama Dengan",
          "url": "https://www.zomato.com/bandung/sama-dengan-cihampelas?utm_source=api_basic_user&utm_medium=api&utm_campaign=v2.1",
          "location": {
            "address": "Cihampelas Walk, Lantai Ground, Jl. Cihampelas No. 160, Cihampelas, Bandung 40131",
            "locality": "Cihampelas Walk, Cihampelas",
            "city": "Bandung",
            "city_id": 11052,
            "latitude": "-6.8942930000",
            "longitude": "107.6052680000",
            "zipcode": "40131",
            "country_id": 94,
            "locality_verbose": "Cihampelas Walk, Cihampelas, Bandung"
          },
          "switch_to_order_menu": 0,
          "cuisines": "Coffee",
          "average_cost_for_two": 100000,
          "price_range": 2,
          "currency": "IDR",
          "offers": [],
          "opentable_support": 0,
          "is_zomato_book_res": 0,
          "mezzo_provider": "OTHER",
          "is_book_form_web_view": 0,
          "book_form_web_view_url": "",
          "book_again_url": "",
          "thumb": "https://b.zmtcdn.com/data/reviews_photos/895/0cc99c2f9e2494ead434609c653f0895_1535698652.jpg?fit=around%7C200%3A200&crop=200%3A200%3B%2A%2C%2A",
          "user_rating": {
            "aggregate_rating": "4.5",
            "rating_text": "Excellent",
            "rating_color": "3F7E00",
            "votes": "229"
          },
          "photos_url": "https://www.zomato.com/bandung/sama-dengan-cihampelas/photos?utm_source=api_basic_user&utm_medium=api&utm_campaign=v2.1#tabtop",
          "menu_url": "https://www.zomato.com/bandung/sama-dengan-cihampelas/menu?utm_source=api_basic_user&utm_medium=api&utm_campaign=v2.1&openSwipeBox=menu&showMinimal=1#tabtop",
          "featured_image": "https://b.zmtcdn.com/data/reviews_photos/895/0cc99c2f9e2494ead434609c653f0895_1535698652.jpg",
          "has_online_delivery": 0,
          "is_delivering_now": 0,
          "include_bogo_offers": true,
          "deeplink": "zomato://restaurant/18764005",
          "is_table_reservation_supported": 0,
          "has_table_booking": 0,
          "events_url": "https://www.zomato.com/bandung/sama-dengan-cihampelas/events#tabtop?utm_source=api_basic_user&utm_medium=api&utm_campaign=v2.1",
          "establishment_types": []
        }
      },
      {
        "restaurant": {
          "R": {
            "res_id": 18602626
          },
          "apikey": "1b4ca21099641932b900452285be769e",
          "id": "18602626",
          "name": "Gyu-Kaku Japanese BBQ",
          "url": "https://www.zomato.com/bandung/gyu-kaku-japanese-bbq-sukajadi?utm_source=api_basic_user&utm_medium=api&utm_campaign=v2.1",
          "location": {
            "address": "Paris Van Java, Resort Level, Jl. Sukajadi No. 131-139, Sukajadi, Bandung",
            "locality": "Paris Van Java, Sukajadi",
            "city": "Bandung",
            "city_id": 11052,
            "latitude": "-6.8895096516",
            "longitude": "107.5967402011",
            "zipcode": "",
            "country_id": 94,
            "locality_verbose": "Paris Van Java, Sukajadi, Bandung"
          },
          "switch_to_order_menu": 0,
          "cuisines": "Japanese",
          "average_cost_for_two": 300000,
          "price_range": 3,
          "currency": "IDR",
          "offers": [],
          "opentable_support": 0,
          "is_zomato_book_res": 0,
          "mezzo_provider": "OTHER",
          "is_book_form_web_view": 0,
          "book_form_web_view_url": "",
          "book_again_url": "",
          "thumb": "https://b.zmtcdn.com/data/res_imagery/18602626_RESTAURANT_6a90a36a895c53c7097a2fff2f2cb73a.jpg?fit=around%7C200%3A200&crop=200%3A200%3B%2A%2C%2A",
          "user_rating": {
            "aggregate_rating": "4.9",
            "rating_text": "Terbaik",
            "rating_color": "3F7E00",
            "votes": "821"
          },
          "photos_url": "https://www.zomato.com/bandung/gyu-kaku-japanese-bbq-sukajadi/photos?utm_source=api_basic_user&utm_medium=api&utm_campaign=v2.1#tabtop",
          "menu_url": "https://www.zomato.com/bandung/gyu-kaku-japanese-bbq-sukajadi/menu?utm_source=api_basic_user&utm_medium=api&utm_campaign=v2.1&openSwipeBox=menu&showMinimal=1#tabtop",
          "featured_image": "https://b.zmtcdn.com/data/res_imagery/18602626_RESTAURANT_6a90a36a895c53c7097a2fff2f2cb73a.jpg",
          "has_online_delivery": 0,
          "is_delivering_now": 0,
          "include_bogo_offers": true,
          "deeplink": "zomato://restaurant/18602626",
          "is_table_reservation_supported": 0,
          "has_table_booking": 0,
          "events_url": "https://www.zomato.com/bandung/gyu-kaku-japanese-bbq-sukajadi/events#tabtop?utm_source=api_basic_user&utm_medium=api&utm_campaign=v2.1",
          "establishment_types": []
        }
      },
      {
        "restaurant": {
          "R": {
            "res_id": 18407025
          },
          "apikey": "1b4ca21099641932b900452285be769e",
          "id": "18407025",
          "name": "Kalpa Tree ",
          "url": "https://www.zomato.com/bandung/kalpa-tree-ciumbuleuit?utm_source=api_basic_user&utm_medium=api&utm_campaign=v2.1",
          "location": {
            "address": "Jl. Kiputih No. 37, Ciumbuleuit, Bandung",
            "locality": "Ciumbuleuit",
            "city": "Bandung",
            "city_id": 11052,
            "latitude": "-6.8662014000",
            "longitude": "107.6082161000",
            "zipcode": "",
            "country_id": 94,
            "locality_verbose": "Ciumbuleuit, Bandung"
          },
          "switch_to_order_menu": 0,
          "cuisines": "Western, Indonesian",
          "average_cost_for_two": 200000,
          "price_range": 3,
          "currency": "IDR",
          "offers": [],
          "opentable_support": 0,
          "is_zomato_book_res": 0,
          "mezzo_provider": "OTHER",
          "is_book_form_web_view": 0,
          "book_form_web_view_url": "",
          "book_again_url": "",
          "thumb": "https://b.zmtcdn.com/data/res_imagery/18407025_RESTAURANT_cdc5fcd93b9754c143dfdd0703641dc3.jpg?fit=around%7C200%3A200&crop=200%3A200%3B%2A%2C%2A",
          "user_rating": {
            "aggregate_rating": "4.4",
            "rating_text": "Very Good",
            "rating_color": "5BA829",
            "votes": "413"
          },
          "photos_url": "https://www.zomato.com/bandung/kalpa-tree-ciumbuleuit/photos?utm_source=api_basic_user&utm_medium=api&utm_campaign=v2.1#tabtop",
          "menu_url": "https://www.zomato.com/bandung/kalpa-tree-ciumbuleuit/menu?utm_source=api_basic_user&utm_medium=api&utm_campaign=v2.1&openSwipeBox=menu&showMinimal=1#tabtop",
          "featured_image": "https://b.zmtcdn.com/data/res_imagery/18407025_RESTAURANT_cdc5fcd93b9754c143dfdd0703641dc3.jpg",
          "has_online_delivery": 0,
          "is_delivering_now": 0,
          "include_bogo_offers": true,
          "deeplink": "zomato://restaurant/18407025",
          "is_table_reservation_supported": 0,
          "has_table_booking": 0,
          "events_url": "https://www.zomato.com/bandung/kalpa-tree-ciumbuleuit/events#tabtop?utm_source=api_basic_user&utm_medium=api&utm_campaign=v2.1",
          "establishment_types": []
        }
      },
      {
        "restaurant": {
          "R": {
            "res_id": 18404792
          },
          "apikey": "1b4ca21099641932b900452285be769e",
          "id": "18404792",
          "name": "Sydwic",
          "url": "https://www.zomato.com/bandung/sydwic-riau?utm_source=api_basic_user&utm_medium=api&utm_campaign=v2.1",
          "location": {
            "address": "Jl. Cilaki No. 63, Riau, Bandung",
            "locality": "Riau",
            "city": "Bandung",
            "city_id": 11052,
            "latitude": "-6.9035109990",
            "longitude": "107.6222007349",
            "zipcode": "",
            "country_id": 94,
            "locality_verbose": "Riau, Bandung"
          },
          "switch_to_order_menu": 0,
          "cuisines": "Cafe, Western, Asian, Coffee, Tea",
          "average_cost_for_two": 150000,
          "price_range": 3,
          "currency": "IDR",
          "offers": [],
          "opentable_support": 0,
          "is_zomato_book_res": 0,
          "mezzo_provider": "OTHER",
          "is_book_form_web_view": 0,
          "book_form_web_view_url": "",
          "book_again_url": "",
          "thumb": "https://b.zmtcdn.com/data/res_imagery/18404792_RESTAURANT_10d737685cd27fc63ad2b5cf2838e4a1.jpg?fit=around%7C200%3A200&crop=200%3A200%3B%2A%2C%2A",
          "user_rating": {
            "aggregate_rating": "4.2",
            "rating_text": "Very Good",
            "rating_color": "5BA829",
            "votes": "210"
          },
          "photos_url": "https://www.zomato.com/bandung/sydwic-riau/photos?utm_source=api_basic_user&utm_medium=api&utm_campaign=v2.1#tabtop",
          "menu_url": "https://www.zomato.com/bandung/sydwic-riau/menu?utm_source=api_basic_user&utm_medium=api&utm_campaign=v2.1&openSwipeBox=menu&showMinimal=1#tabtop",
          "featured_image": "https://b.zmtcdn.com/data/res_imagery/18404792_RESTAURANT_10d737685cd27fc63ad2b5cf2838e4a1.jpg",
          "has_online_delivery": 0,
          "is_delivering_now": 0,
          "include_bogo_offers": true,
          "deeplink": "zomato://restaurant/18404792",
          "is_table_reservation_supported": 0,
          "has_table_booking": 0,
          "events_url": "https://www.zomato.com/bandung/sydwic-riau/events#tabtop?utm_source=api_basic_user&utm_medium=api&utm_campaign=v2.1",
          "establishment_types": []
        }
      },
      {
        "restaurant": {
          "R": {
            "res_id": 18400530
          },
          "apikey": "1b4ca21099641932b900452285be769e",
          "id": "18400530",
          "name": "Noah's Barn Coffeenery",
          "url": "https://www.zomato.com/bandung/noahs-barn-coffeenery-dago?utm_source=api_basic_user&utm_medium=api&utm_campaign=v2.1",
          "location": {
            "address": "Jl. Dayang Sumbi No. 2, Dago, Bandung",
            "locality": "Dago",
            "city": "Bandung",
            "city_id": 11052,
            "latitude": "-6.8870575010",
            "longitude": "107.6127895340",
            "zipcode": "",
            "country_id": 94,
            "locality_verbose": "Dago, Bandung"
          },
          "switch_to_order_menu": 0,
          "cuisines": "Cafe, Western, Coffee, Tea",
          "average_cost_for_two": 150000,
          "price_range": 3,
          "currency": "IDR",
          "offers": [],
          "opentable_support": 0,
          "is_zomato_book_res": 0,
          "mezzo_provider": "OTHER",
          "is_book_form_web_view": 0,
          "book_form_web_view_url": "",
          "book_again_url": "",
          "thumb": "",
          "user_rating": {
            "aggregate_rating": "4.4",
            "rating_text": "Very Good",
            "rating_color": "5BA829",
            "votes": "260"
          },
          "photos_url": "https://www.zomato.com/bandung/noahs-barn-coffeenery-dago/photos?utm_source=api_basic_user&utm_medium=api&utm_campaign=v2.1#tabtop",
          "menu_url": "https://www.zomato.com/bandung/noahs-barn-coffeenery-dago/menu?utm_source=api_basic_user&utm_medium=api&utm_campaign=v2.1&openSwipeBox=menu&showMinimal=1#tabtop",
          "featured_image": "",
          "has_online_delivery": 0,
          "is_delivering_now": 0,
          "include_bogo_offers": true,
          "deeplink": "zomato://restaurant/18400530",
          "is_table_reservation_supported": 0,
          "has_table_booking": 0,
          "events_url": "https://www.zomato.com/bandung/noahs-barn-coffeenery-dago/events#tabtop?utm_source=api_basic_user&utm_medium=api&utm_campaign=v2.1",
          "establishment_types": []
        }
      },
      {
        "restaurant": {
          "R": {
            "res_id": 18477915
          },
          "apikey": "1b4ca21099641932b900452285be769e",
          "id": "18477915",
          "name": "Ambrogio Patisserie",
          "url": "https://www.zomato.com/bandung/ambrogio-patisserie-riau?utm_source=api_basic_user&utm_medium=api&utm_campaign=v2.1",
          "location": {
            "address": "Jl. Banda No. 26, Riau, Bandung",
            "locality": "Riau",
            "city": "Bandung",
            "city_id": 11052,
            "latitude": "-6.9079890000",
            "longitude": "107.6175050000",
            "zipcode": "",
            "country_id": 94,
            "locality_verbose": "Riau, Bandung"
          },
          "switch_to_order_menu": 0,
          "cuisines": "Western, Desserts, Coffee",
          "average_cost_for_two": 150000,
          "price_range": 3,
          "currency": "IDR",
          "offers": [],
          "opentable_support": 0,
          "is_zomato_book_res": 0,
          "mezzo_provider": "OTHER",
          "is_book_form_web_view": 0,
          "book_form_web_view_url": "",
          "book_again_url": "",
          "thumb": "https://b.zmtcdn.com/data/res_imagery/18477915_RESTAURANT_1d9c345f046c58d8606cb2c81556726d.jpg?fit=around%7C200%3A200&crop=200%3A200%3B%2A%2C%2A",
          "user_rating": {
            "aggregate_rating": "4.6",
            "rating_text": "Excellent",
            "rating_color": "3F7E00",
            "votes": "248"
          },
          "photos_url": "https://www.zomato.com/bandung/ambrogio-patisserie-riau/photos?utm_source=api_basic_user&utm_medium=api&utm_campaign=v2.1#tabtop",
          "menu_url": "https://www.zomato.com/bandung/ambrogio-patisserie-riau/menu?utm_source=api_basic_user&utm_medium=api&utm_campaign=v2.1&openSwipeBox=menu&showMinimal=1#tabtop",
          "featured_image": "https://b.zmtcdn.com/data/res_imagery/18477915_RESTAURANT_1d9c345f046c58d8606cb2c81556726d.jpg",
          "has_online_delivery": 0,
          "is_delivering_now": 0,
          "include_bogo_offers": true,
          "deeplink": "zomato://restaurant/18477915",
          "is_table_reservation_supported": 0,
          "has_table_booking": 0,
          "events_url": "https://www.zomato.com/bandung/ambrogio-patisserie-riau/events#tabtop?utm_source=api_basic_user&utm_medium=api&utm_campaign=v2.1",
          "establishment_types": []
        }
      },
      {
        "restaurant": {
          "R": {
            "res_id": 18387839
          },
          "apikey": "1b4ca21099641932b900452285be769e",
          "id": "18387839",
          "name": "Karnivor",
          "url": "https://www.zomato.com/bandung/karnivor-riau?utm_source=api_basic_user&utm_medium=api&utm_campaign=v2.1",
          "location": {
            "address": "Jl. L.L.R.E. Martadinata No. 127, Riau, Bandung",
            "locality": "Riau",
            "city": "Bandung",
            "city_id": 11052,
            "latitude": "-6.9079840867",
            "longitude": "107.6238489524",
            "zipcode": "",
            "country_id": 94,
            "locality_verbose": "Riau, Bandung"
          },
          "switch_to_order_menu": 0,
          "cuisines": "Grill",
          "average_cost_for_two": 150000,
          "price_range": 3,
          "currency": "IDR",
          "offers": [],
          "opentable_support": 0,
          "is_zomato_book_res": 0,
          "mezzo_provider": "OTHER",
          "is_book_form_web_view": 0,
          "book_form_web_view_url": "",
          "book_again_url": "",
          "thumb": "https://b.zmtcdn.com/data/res_imagery/18387839_RESTAURANT_e4582f007bd7f3d15ae5e57d0ac077af.jpg?fit=around%7C200%3A200&crop=200%3A200%3B%2A%2C%2A",
          "user_rating": {
            "aggregate_rating": "4.2",
            "rating_text": "Very Good",
            "rating_color": "5BA829",
            "votes": "283"
          },
          "photos_url": "https://www.zomato.com/bandung/karnivor-riau/photos?utm_source=api_basic_user&utm_medium=api&utm_campaign=v2.1#tabtop",
          "menu_url": "https://www.zomato.com/bandung/karnivor-riau/menu?utm_source=api_basic_user&utm_medium=api&utm_campaign=v2.1&openSwipeBox=menu&showMinimal=1#tabtop",
          "featured_image": "https://b.zmtcdn.com/data/res_imagery/18387839_RESTAURANT_e4582f007bd7f3d15ae5e57d0ac077af.jpg",
          "has_online_delivery": 0,
          "is_delivering_now": 0,
          "include_bogo_offers": true,
          "deeplink": "zomato://restaurant/18387839",
          "is_table_reservation_supported": 0,
          "has_table_booking": 0,
          "events_url": "https://www.zomato.com/bandung/karnivor-riau/events#tabtop?utm_source=api_basic_user&utm_medium=api&utm_campaign=v2.1",
          "establishment_types": []
        }
      },
      {
        "restaurant": {
          "R": {
            "res_id": 18389079
          },
          "apikey": "1b4ca21099641932b900452285be769e",
          "id": "18389079",
          "name": "Rumah Makan Alas Daun",
          "url": "https://www.zomato.com/bandung/rumah-makan-alas-daun-riau?utm_source=api_basic_user&utm_medium=api&utm_campaign=v2.1",
          "location": {
            "address": "Jl. Citarum No. 34, Riau, Bandung",
            "locality": "Riau",
            "city": "Bandung",
            "city_id": 11052,
            "latitude": "-6.9018873765",
            "longitude": "107.6252178848",
            "zipcode": "",
            "country_id": 94,
            "locality_verbose": "Riau, Bandung"
          },
          "switch_to_order_menu": 0,
          "cuisines": "Sunda, Indonesian",
          "average_cost_for_two": 150000,
          "price_range": 3,
          "currency": "IDR",
          "offers": [],
          "opentable_support": 0,
          "is_zomato_book_res": 0,
          "mezzo_provider": "OTHER",
          "is_book_form_web_view": 0,
          "book_form_web_view_url": "",
          "book_again_url": "",
          "thumb": "https://b.zmtcdn.com/data/res_imagery/18389079_RESTAURANT_e805a0f0770094cb5a846504ac93cf03.JPG?fit=around%7C200%3A200&crop=200%3A200%3B%2A%2C%2A",
          "user_rating": {
            "aggregate_rating": "4.3",
            "rating_text": "Very Good",
            "rating_color": "5BA829",
            "votes": "161"
          },
          "photos_url": "https://www.zomato.com/bandung/rumah-makan-alas-daun-riau/photos?utm_source=api_basic_user&utm_medium=api&utm_campaign=v2.1#tabtop",
          "menu_url": "https://www.zomato.com/bandung/rumah-makan-alas-daun-riau/menu?utm_source=api_basic_user&utm_medium=api&utm_campaign=v2.1&openSwipeBox=menu&showMinimal=1#tabtop",
          "featured_image": "https://b.zmtcdn.com/data/res_imagery/18389079_RESTAURANT_e805a0f0770094cb5a846504ac93cf03.JPG",
          "has_online_delivery": 0,
          "is_delivering_now": 0,
          "include_bogo_offers": true,
          "deeplink": "zomato://restaurant/18389079",
          "is_table_reservation_supported": 0,
          "has_table_booking": 0,
          "events_url": "https://www.zomato.com/bandung/rumah-makan-alas-daun-riau/events#tabtop?utm_source=api_basic_user&utm_medium=api&utm_campaign=v2.1",
          "establishment_types": []
        }
      },
      {
        "restaurant": {
          "R": {
            "res_id": 18389240
          },
          "apikey": "1b4ca21099641932b900452285be769e",
          "id": "18389240",
          "name": "Chingu Cafe",
          "url": "https://www.zomato.com/bandung/chingu-cafe-bandung-wetan?utm_source=api_basic_user&utm_medium=api&utm_campaign=v2.1",
          "location": {
            "address": "Jl. Sawunggaling No. 10, Bandung Wetan, Bandung",
            "locality": "Bandung Wetan",
            "city": "Bandung",
            "city_id": 11052,
            "latitude": "-6.9012779341",
            "longitude": "107.6098072529",
            "zipcode": "",
            "country_id": 94,
            "locality_verbose": "Bandung Wetan, Bandung"
          },
          "switch_to_order_menu": 0,
          "cuisines": "Cafe",
          "average_cost_for_two": 70000,
          "price_range": 1,
          "currency": "IDR",
          "offers": [],
          "opentable_support": 0,
          "is_zomato_book_res": 0,
          "mezzo_provider": "OTHER",
          "is_book_form_web_view": 0,
          "book_form_web_view_url": "",
          "book_again_url": "",
          "thumb": "https://b.zmtcdn.com/data/res_imagery/18389240_RESTAURANT_6b7584c70c26e6f3f92ae1af032cb3bb.jpg?fit=around%7C200%3A200&crop=200%3A200%3B%2A%2C%2A",
          "user_rating": {
            "aggregate_rating": "3.7",
            "rating_text": "Good",
            "rating_color": "9ACD32",
            "votes": "201"
          },
          "photos_url": "https://www.zomato.com/bandung/chingu-cafe-bandung-wetan/photos?utm_source=api_basic_user&utm_medium=api&utm_campaign=v2.1#tabtop",
          "menu_url": "https://www.zomato.com/bandung/chingu-cafe-bandung-wetan/menu?utm_source=api_basic_user&utm_medium=api&utm_campaign=v2.1&openSwipeBox=menu&showMinimal=1#tabtop",
          "featured_image": "https://b.zmtcdn.com/data/res_imagery/18389240_RESTAURANT_6b7584c70c26e6f3f92ae1af032cb3bb.jpg",
          "has_online_delivery": 0,
          "is_delivering_now": 0,
          "include_bogo_offers": true,
          "deeplink": "zomato://restaurant/18389240",
          "is_table_reservation_supported": 0,
          "has_table_booking": 0,
          "events_url": "https://www.zomato.com/bandung/chingu-cafe-bandung-wetan/events#tabtop?utm_source=api_basic_user&utm_medium=api&utm_campaign=v2.1",
          "establishment_types": []
        }
      },
      {
        "restaurant": {
          "R": {
            "res_id": 18389279
          },
          "apikey": "1b4ca21099641932b900452285be769e",
          "id": "18389279",
          "name": "Armor Kopi",
          "url": "https://www.zomato.com/bandung/armor-kopi-dago-pakar?utm_source=api_basic_user&utm_medium=api&utm_campaign=v2.1",
          "location": {
            "address": "Jl. Bukit Pakar Utara No. 10, Dago Pakar, Bandung",
            "locality": "Dago Pakar",
            "city": "Bandung",
            "city_id": 11052,
            "latitude": "-6.8583350742",
            "longitude": "107.6305256411",
            "zipcode": "",
            "country_id": 94,
            "locality_verbose": "Dago Pakar, Bandung"
          },
          "switch_to_order_menu": 0,
          "cuisines": "Cafe, Coffee, Tea",
          "average_cost_for_two": 75000,
          "price_range": 1,
          "currency": "IDR",
          "offers": [],
          "opentable_support": 0,
          "is_zomato_book_res": 0,
          "mezzo_provider": "OTHER",
          "is_book_form_web_view": 0,
          "book_form_web_view_url": "",
          "book_again_url": "",
          "thumb": "https://b.zmtcdn.com/data/res_imagery/18389279_RESTAURANT_9bce920b76b57b39295c30a7879613f2.jpg?fit=around%7C200%3A200&crop=200%3A200%3B%2A%2C%2A",
          "user_rating": {
            "aggregate_rating": "4.4",
            "rating_text": "Very Good",
            "rating_color": "5BA829",
            "votes": "236"
          },
          "photos_url": "https://www.zomato.com/bandung/armor-kopi-dago-pakar/photos?utm_source=api_basic_user&utm_medium=api&utm_campaign=v2.1#tabtop",
          "menu_url": "https://www.zomato.com/bandung/armor-kopi-dago-pakar/menu?utm_source=api_basic_user&utm_medium=api&utm_campaign=v2.1&openSwipeBox=menu&showMinimal=1#tabtop",
          "featured_image": "https://b.zmtcdn.com/data/res_imagery/18389279_RESTAURANT_9bce920b76b57b39295c30a7879613f2.jpg",
          "has_online_delivery": 0,
          "is_delivering_now": 0,
          "include_bogo_offers": true,
          "deeplink": "zomato://restaurant/18389279",
          "is_table_reservation_supported": 0,
          "has_table_booking": 0,
          "events_url": "https://www.zomato.com/bandung/armor-kopi-dago-pakar/events#tabtop?utm_source=api_basic_user&utm_medium=api&utm_campaign=v2.1",
          "establishment_types": []
        }
      },
      {
        "restaurant": {
          "R": {
            "res_id": 18389277
          },
          "apikey": "1b4ca21099641932b900452285be769e",
          "id": "18389277",
          "name": "Lereng Anteng",
          "url": "https://www.zomato.com/bandung/lereng-anteng-lembang?utm_source=api_basic_user&utm_medium=api&utm_campaign=v2.1",
          "location": {
            "address": "Jl. Baru Laksana No. 75, Lembang, Bandung",
            "locality": "Lembang",
            "city": "Bandung",
            "city_id": 11052,
            "latitude": "-6.8425824067",
            "longitude": "107.6226489991",
            "zipcode": "",
            "country_id": 94,
            "locality_verbose": "Lembang, Bandung"
          },
          "switch_to_order_menu": 0,
          "cuisines": "Cafe, Coffee",
          "average_cost_for_two": 60000,
          "price_range": 1,
          "currency": "IDR",
          "offers": [],
          "opentable_support": 0,
          "is_zomato_book_res": 0,
          "mezzo_provider": "OTHER",
          "is_book_form_web_view": 0,
          "book_form_web_view_url": "",
          "book_again_url": "",
          "thumb": "https://b.zmtcdn.com/data/res_imagery/18389277_RESTAURANT_ef296a040d14e41f0907dfdaef2dce67.JPG?fit=around%7C200%3A200&crop=200%3A200%3B%2A%2C%2A",
          "user_rating": {
            "aggregate_rating": "3.9",
            "rating_text": "Good",
            "rating_color": "9ACD32",
            "votes": "279"
          },
          "photos_url": "https://www.zomato.com/bandung/lereng-anteng-lembang/photos?utm_source=api_basic_user&utm_medium=api&utm_campaign=v2.1#tabtop",
          "menu_url": "https://www.zomato.com/bandung/lereng-anteng-lembang/menu?utm_source=api_basic_user&utm_medium=api&utm_campaign=v2.1&openSwipeBox=menu&showMinimal=1#tabtop",
          "featured_image": "https://b.zmtcdn.com/data/res_imagery/18389277_RESTAURANT_ef296a040d14e41f0907dfdaef2dce67.JPG",
          "has_online_delivery": 0,
          "is_delivering_now": 0,
          "include_bogo_offers": true,
          "deeplink": "zomato://restaurant/18389277",
          "is_table_reservation_supported": 0,
          "has_table_booking": 0,
          "events_url": "https://www.zomato.com/bandung/lereng-anteng-lembang/events#tabtop?utm_source=api_basic_user&utm_medium=api&utm_campaign=v2.1",
          "establishment_types": []
        }
      },
      {
        "restaurant": {
          "R": {
            "res_id": 18756491
          },
          "apikey": "1b4ca21099641932b900452285be769e",
          "id": "18756491",
          "name": "Jardin Cafe",
          "url": "https://www.zomato.com/bandung/jardin-cafe-riau?utm_source=api_basic_user&utm_medium=api&utm_campaign=v2.1",
          "location": {
            "address": "Jl. Cimanuk No. 1, Riau, Bandung",
            "locality": "Riau",
            "city": "Bandung",
            "city_id": 11052,
            "latitude": "-6.9053502989",
            "longitude": "107.6203748211",
            "zipcode": "",
            "country_id": 94,
            "locality_verbose": "Riau, Bandung"
          },
          "switch_to_order_menu": 0,
          "cuisines": "Italian, Western",
          "average_cost_for_two": 200000,
          "price_range": 3,
          "currency": "IDR",
          "offers": [],
          "opentable_support": 0,
          "is_zomato_book_res": 0,
          "mezzo_provider": "OTHER",
          "is_book_form_web_view": 0,
          "book_form_web_view_url": "",
          "book_again_url": "",
          "thumb": "",
          "user_rating": {
            "aggregate_rating": "3.7",
            "rating_text": "Good",
            "rating_color": "9ACD32",
            "votes": "71"
          },
          "photos_url": "https://www.zomato.com/bandung/jardin-cafe-riau/photos?utm_source=api_basic_user&utm_medium=api&utm_campaign=v2.1#tabtop",
          "menu_url": "https://www.zomato.com/bandung/jardin-cafe-riau/menu?utm_source=api_basic_user&utm_medium=api&utm_campaign=v2.1&openSwipeBox=menu&showMinimal=1#tabtop",
          "featured_image": "",
          "has_online_delivery": 0,
          "is_delivering_now": 0,
          "include_bogo_offers": true,
          "deeplink": "zomato://restaurant/18756491",
          "is_table_reservation_supported": 0,
          "has_table_booking": 0,
          "events_url": "https://www.zomato.com/bandung/jardin-cafe-riau/events#tabtop?utm_source=api_basic_user&utm_medium=api&utm_campaign=v2.1",
          "establishment_types": []
        }
      }
    ]
  }